servalcat/__init__.py
servalcat/__main__.py
servalcat/ext.cp310-win_amd64.pyd
servalcat/refine/__init__.py
servalcat/refine/cgsolve.py
servalcat/refine/refine.py
servalcat/refine/refine_geom.py
servalcat/refine/refine_spa.py
servalcat/refine/refine_xtal.py
servalcat/refine/spa.py
servalcat/refine/xtal.py
servalcat/refmac/__init__.py
servalcat/refmac/exte.py
servalcat/refmac/refmac_keywords.py
servalcat/refmac/refmac_wrapper.py
servalcat/spa/__init__.py
servalcat/spa/fofc.py
servalcat/spa/fsc.py
servalcat/spa/localcc.py
servalcat/spa/realspcc_from_var.py
servalcat/spa/run_refmac.py
servalcat/spa/shift_maps.py
servalcat/spa/shiftback.py
servalcat/spa/translate.py
servalcat/utils/__init__.py
servalcat/utils/commands.py
servalcat/utils/fileio.py
servalcat/utils/generate_operators.py
servalcat/utils/hkl.py
servalcat/utils/logger.py
servalcat/utils/maps.py
servalcat/utils/model.py
servalcat/utils/refmac.py
servalcat/utils/restraints.py
servalcat/utils/symmetry.py
servalcat/xtal/__init__.py
servalcat/xtal/french_wilson.py
servalcat/xtal/run_refmac_small.py
servalcat/xtal/sigmaa.py
servalcat/xtal/twin.py
servalcat-0.4.126.dist-info/METADATA
servalcat-0.4.126.dist-info/WHEEL
servalcat-0.4.126.dist-info/entry_points.txt
servalcat-0.4.126.dist-info/licenses/LICENSE
servalcat-0.4.126.dist-info/RECORD
