Metadata-Version: 2.2
Name: servalcat
Version: 0.4.126
Summary: Structure refinement and validation for crystallography and single particle analysis
Author: Keitaro Yamashita, Garib N. Murshudov
License: MPL-2.0
Project-URL: repository, https://github.com/keitaroyam/servalcat
Requires-Python: >=3.8
Requires-Dist: packaging
Requires-Dist: numpy>=1.15
Requires-Dist: scipy
Requires-Dist: pandas>=1.1.0
Requires-Dist: omegaconf==2.3.0
Requires-Dist: gemmi==0.7.3
